Metadata-Version: 1.0
Name: pipcudemo
Version: 1.0.2
Summary: An example project showing how to build a pip-installable Python package that invokes custom CUDA/C++ code.
Home-page: UNKNOWN
Author: Alan (AJ) Pryor, Jr.
Author-email: apryor6@gmail.com
License: UNKNOWN
Platform: UNKNOWN
